Metadata-Version: 1.0
Name: dsnd-probability-shahid
Version: 0.1
Summary: Gaussian and Binomial distributions
Home-page: UNKNOWN
Author: Shahid ul Islam
Author-email: shahid.bhat1994@gmail.com
License: UNKNOWN
Platform: UNKNOWN
